{
  "generated_at": 1772888893.388887,
  "repo_root": "/mnt/c/MyCode/SemantiK_Architect/Semantik_architect",
  "summary": {
    "compile_valid_or_skipped": 2,
    "compile_broken": 0,
    "runtime_pass": 2,
    "runtime_fail": 0,
    "overall_ok": 2,
    "overall_fail": 0
  },
  "results": [
    {
      "gf_lang": "Eng",
      "api_lang": "en",
      "overall": "OK",
      "compile": {
        "gf_lang": "Eng",
        "filename": "gf/WikiEng.gf",
        "status": "SKIPPED",
        "error": null,
        "duration_s": 0.0,
        "file_hash": "6e6a7236e78edf879478bd01f73ac0caa98806a00b5d34b8fda0281ec84aac32",
        "iso2": "en"
      },
      "runtime": {
        "api_lang": "en",
        "status": "PASS",
        "http_status": 200,
        "duration_ms": 28.63597869873047,
        "error": null,
        "sample_text": "Shaka is a zulu warrior"
      }
    },
    {
      "gf_lang": "Fre",
      "api_lang": "fr",
      "overall": "OK",
      "compile": {
        "gf_lang": "Fre",
        "filename": "gf/WikiFre.gf",
        "status": "VALID",
        "error": null,
        "duration_s": 6.382803201675415,
        "file_hash": "b257203563f5dc6534db65d37a53c07ba10573de12148dca5bc4f8297bb673f0",
        "iso2": "fr"
      },
      "runtime": {
        "api_lang": "fr",
        "status": "PASS",
        "http_status": 200,
        "duration_ms": 27.26602554321289,
        "error": null,
        "sample_text": "Shaka is a warrior ( zulu )"
      }
    }
  ]
}