{
  "_meta": {
    "language": "fa",
    "domain": "geography",
    "version": 1
  },
  "entries": {
    "irani": {
      "pos": "ADJ",
      "gloss": "Iranian",
      "degree": "positive",
      "nationality": true,
      "derived_from": "iran"
    },
    "faransavi": {
      "pos": "ADJ",
      "gloss": "French",
      "degree": "positive",
      "nationality": true,
      "derived_from": "farans"
    },
    "almani": {
      "pos": "ADJ",
      "gloss": "German",
      "degree": "positive",
      "nationality": true,
      "derived_from": "alman"
    },
    "lahestani": {
      "pos": "ADJ",
      "gloss": "Polish",
      "degree": "positive",
      "nationality": true,
      "derived_from": "lahestan"
    },
    "amerikai": {
      "pos": "ADJ",
      "gloss": "American",
      "degree": "positive",
      "nationality": true
    }
  }
}